{
  "target": "pt",
  "lang": "pt",
  "cta": true,
  "image": "assets/signals/ban-long-20260627.jpg",
  "body": "🔥 Sinal VIP grátis — normalmente só para pagantes\n\nUm sinal ao vivo da sala VIP. Vamos soltar UM de graça pra você ver exatamente o que os membros recebem 👇\n\n🔺 #Signal · LC-0627\n\nBAN/USDT — LONG\nEntry: 0.0731\nAlvo: 0.0757\nSL: 0.0727   ← hard stop, defina ANTES da entry\n\n📏 Tamanho pequeno. A leverage pode ser agressiva — o tamanho da posição não. Risco ≤1–2% por ideia.\n🧭 Base: reclaim no 15m acima do suporte, stop abaixo da mínima local, alvo na máxima do swing anterior.\n\n🔒 No VIP cada sinal sai ao vivo, em tempo real — entries, níveis e o raciocínio por trás de cada call. Este de graça é só a amostra.\n🎟 Comece um trial grátis de 30 dias e receba todos 👉 {{COMMUNITY}}\n\n#Signal"
}
