{
  "id": "en-education-001",
  "channel": "en",
  "rubric": "education",
  "slot": null,
  "lang": "en",
  "ready": true,
  "cta": true,
  "title": "Funding rate — why we read it before every signal",
  "_note": "EVERGREEN v2 (#CryptoSchool). Retoned to Variant B (data-check edge). Numeric example replaced with NEUTRAL wording (no invented numbers); CTA via {{COMMUNITY}} marker (dropped if COMMUNITY_LINK empty). No placeholders → ready.",
  "body": "🎓 Funding rate — and why we read it before every signal\n\nWhat it is\nOn perpetual futures, funding is a small periodic payment passed directly between longs and shorts. It's what keeps the perp price tethered to spot.\n\nWhy we care (and you should)\nFunding tells you which side is crowded. Strongly positive = longs are paying shorts — everyone's leaning long, and you're paying to sit there. Strongly negative = the opposite. At extremes, the crowded side is exactly the side that gets liquidated first.\n\nHow we use it\nBefore any signal ships, we pull funding straight off Bitunix (aggregators don't cover it) and overlay the liquidation heatmap. Two things come out of that:\n• Extreme funding → the crowd is offside → we lean toward fading, not following.\n• We place the SL AWAY from the liquidation magnet, not on top of it — so a stop-hunt wick doesn't take us out before the idea plays.\n\nQuick example\nWhen funding is positive and you hold a long, you pay a small amount to the shorts at each funding interval. Tiny per interval — but at 50-100x it compounds fast, and the exact figure depends on the live funding rate and your position size. Check it on the exchange and price it in before you enter.\n\nThis is the kind of data-check behind every #Signal we post. Questions about funding? Ask in the community — that's what it's for. 👉 {{COMMUNITY}}\n\n#CryptoSchool"
}
