{
  "id": "pnl-20260625-skr-short-id",
  "channel": "id",
  "rubric": "pnl",
  "slot": null,
  "lang": "id",
  "ready": true,
  "cta": false,
  "title": "SKR Short 20x +17.58% (ID)",
  "image": "assets/pnl/pnl-20260625-skr-short.png",
  "body": "📊 Verified P&L — SKR/USDT Short · 20x · +17.58% (1h09m)\n\nIde-nya: kami short SKR setelah dorongan cepat kehabisan tenaga dan gagal menahan high-nya — kami fade kelelahannya.\n\nRisikonya: stop duduk tepat di atas swing high yang membatasi dorongan itu, diset sebelum kami entry — 20x yang moderat, tapi garis di mana kami akan salah digambar lebih dulu, bukan belakangan.\n\nPerhatikan, yang ini bukan pamer 100x. Leverage lebih kecil, disiplin yang sama. Ukuran multiplier bukan yang membuat trade ini berhasil — tahu titik keluar-kalau-salah sebelum klik buy-lah yang membuatnya. Rencanakan kerugiannya dulu, baru beri posisinya ruang bernapas.\n\n⚠️ Ini hasil masa lalu, bukan prediksi. High leverage = risiko kerugian total yang tinggi. Hanya untuk edukasi, bukan nasihat keuangan.\n\n#HasilNyata"
}
